[
  {
    "id": 1,
    "title": "Second place winner of the UMM Code Championship",
    "image": "certificate1.jpeg"
  },
  {
    "id": 2,
    "title": "Contestant of the LKS Wilker 3 in 2022",
    "image": "certificate2.jpeg"
  },
  {
    "id": 3,
    "title": "Participant of the Pasuruandev Webinar",
    "image": "certificate3.jpeg"
  },
  {
    "id": 4,
    "title": "Participant of the Technowars Seminar",
    "image": "certificate4.jpeg"
  },
  {
    "id": 5,
    "title": "Participant of the National Seminar Filkom UB",
    "image": "certificate5.jpeg"
  },
  {
    "id": 6,
    "title": "Participant of the 4C Competition Filkom UB",
    "image": "certificate6.jpeg"
  },
  {
    "id": 7,
    "title": "Fundamentals Of Dark Web Training",
    "image": "certificate7.jpeg"
  }
]